[{"hash":"","decodedHash":[],"edition":1,"date":1644291087565,"attributes":[]},{"hash":"","decodedHash":[],"edition":2,"date":1644291088355,"attributes":[]},{"hash":"","decodedHash":[],"edition":3,"date":1644291089142,"attributes":[]},{"hash":"","decodedHash":[],"edition":4,"date":1644291089615,"attributes":[]},{"hash":"","decodedHash":[],"edition":5,"date":1644291090273,"attributes":[]},{"hash":"","decodedHash":[],"edition":6,"date":1644291090901,"attributes":[]},{"hash":"","decodedHash":[],"edition":7,"date":1644291091536,"attributes":[]},{"hash":"","decodedHash":[],"edition":8,"date":1644291092017,"attributes":[]},{"hash":"","decodedHash":[],"edition":9,"date":1644291092822,"attributes":[]},{"hash":"","decodedHash":[],"edition":10,"date":1644291093499,"attributes":[]},{"hash":"","decodedHash":[],"edition":11,"date":1644291094391,"attributes":[]},{"hash":"","decodedHash":[],"edition":12,"date":1644291094734,"attributes":[]},{"hash":"","decodedHash":[],"edition":13,"date":1644291095227,"attributes":[]},{"hash":"","decodedHash":[],"edition":14,"date":1644291095873,"attributes":[]},{"hash":"","decodedHash":[],"edition":15,"date":1644291096562,"attributes":[]},{"hash":"","decodedHash":[],"edition":16,"date":1644291097054,"attributes":[]},{"hash":"","decodedHash":[],"edition":17,"date":1644291097392,"attributes":[]},{"hash":"","decodedHash":[],"edition":18,"date":1644291098074,"attributes":[]},{"hash":"","decodedHash":[],"edition":19,"date":1644291098577,"attributes":[]},{"hash":"","decodedHash":[],"edition":20,"date":1644291099422,"attributes":[]},{"hash":"","decodedHash":[],"edition":21,"date":1644291099924,"attributes":[]},{"hash":"","decodedHash":[],"edition":22,"date":1644291100678,"attributes":[]},{"hash":"","decodedHash":[],"edition":23,"date":1644291101587,"attributes":[]},{"hash":"","decodedHash":[],"edition":24,"date":1644291102344,"attributes":[]},{"hash":"","decodedHash":[],"edition":25,"date":1644291102883,"attributes":[]},{"hash":"","decodedHash":[],"edition":26,"date":1644291103728,"attributes":[]},{"hash":"","decodedHash":[],"edition":27,"date":1644291104126,"attributes":[]},{"hash":"","decodedHash":[],"edition":28,"date":1644291105044,"attributes":[]},{"hash":"","decodedHash":[],"edition":29,"date":1644291105777,"attributes":[]},{"hash":"","decodedHash":[],"edition":30,"date":1644291106510,"attributes":[]},{"hash":"","decodedHash":[],"edition":31,"date":1644291107075,"attributes":[]},{"hash":"","decodedHash":[],"edition":32,"date":1644291107781,"attributes":[]},{"hash":"","decodedHash":[],"edition":33,"date":1644291108335,"attributes":[]},{"hash":"","decodedHash":[],"edition":34,"date":1644291109227,"attributes":[]},{"hash":"","decodedHash":[],"edition":35,"date":1644291110157,"attributes":[]},{"hash":"","decodedHash":[],"edition":36,"date":1644291110795,"attributes":[]},{"hash":"","decodedHash":[],"edition":37,"date":1644291111444,"attributes":[]},{"hash":"","decodedHash":[],"edition":38,"date":1644291111890,"attributes":[]},{"hash":"","decodedHash":[],"edition":39,"date":1644291112697,"attributes":[]},{"hash":"","decodedHash":[],"edition":40,"date":1644291113517,"attributes":[]},{"hash":"","decodedHash":[],"edition":41,"date":1644291114361,"attributes":[]},{"hash":"","decodedHash":[],"edition":42,"date":1644291115008,"attributes":[]},{"hash":"","decodedHash":[],"edition":43,"date":1644291115652,"attributes":[]},{"hash":"","decodedHash":[],"edition":44,"date":1644291116650,"attributes":[]},{"hash":"","decodedHash":[],"edition":45,"date":1644291117450,"attributes":[]},{"hash":"","decodedHash":[],"edition":46,"date":1644291118301,"attributes":[]},{"hash":"","decodedHash":[],"edition":47,"date":1644291119293,"attributes":[]},{"hash":"","decodedHash":[],"edition":48,"date":1644291120378,"attributes":[]},{"hash":"","decodedHash":[],"edition":49,"date":1644291121260,"attributes":[]},{"hash":"","decodedHash":[],"edition":50,"date":1644291122097,"attributes":[]},{"hash":"","decodedHash":[],"edition":51,"date":1644291123109,"attributes":[]},{"hash":"","decodedHash":[],"edition":52,"date":1644291123725,"attributes":[]},{"hash":"","decodedHash":[],"edition":53,"date":1644291124388,"attributes":[]},{"hash":"","decodedHash":[],"edition":54,"date":1644291125373,"attributes":[]},{"hash":"","decodedHash":[],"edition":55,"date":1644291125982,"attributes":[]},{"hash":"","decodedHash":[],"edition":56,"date":1644291126789,"attributes":[]},{"hash":"","decodedHash":[],"edition":57,"date":1644291127222,"attributes":[]},{"hash":"","decodedHash":[],"edition":58,"date":1644291128266,"attributes":[]},{"hash":"","decodedHash":[],"edition":59,"date":1644291129070,"attributes":[]},{"hash":"","decodedHash":[],"edition":60,"date":1644291130025,"attributes":[]},{"hash":"","decodedHash":[],"edition":61,"date":1644291130657,"attributes":[]},{"hash":"","decodedHash":[],"edition":62,"date":1644291131549,"attributes":[]},{"hash":"","decodedHash":[],"edition":63,"date":1644291132578,"attributes":[]},{"hash":"","decodedHash":[],"edition":64,"date":1644291133433,"attributes":[]},{"hash":"","decodedHash":[],"edition":65,"date":1644291134452,"attributes":[]},{"hash":"","decodedHash":[],"edition":66,"date":1644291134883,"attributes":[]},{"hash":"","decodedHash":[],"edition":67,"date":1644291135689,"attributes":[]},{"hash":"","decodedHash":[],"edition":68,"date":1644291136520,"attributes":[]},{"hash":"","decodedHash":[],"edition":69,"date":1644291137153,"attributes":[]},{"hash":"","decodedHash":[],"edition":70,"date":1644291137766,"attributes":[]},{"hash":"","decodedHash":[],"edition":71,"date":1644291138596,"attributes":[]},{"hash":"","decodedHash":[],"edition":72,"date":1644291139219,"attributes":[]}]